gyropalm_control/__init__.py
gyropalm_control/gp_driving.py
gyropalm_control/gp_realtime.py
gyropalm_control/gp_realtime_robot.py
gyropalm_control-1.1.0.data/data/examples/driving_test.py
gyropalm_control-1.1.0.data/data/examples/realtime_robot_test.py
gyropalm_control-1.1.0.data/data/examples/realtime_test.py
gyropalm_control-1.1.0.dist-info/LICENSE
gyropalm_control-1.1.0.dist-info/METADATA
gyropalm_control-1.1.0.dist-info/WHEEL
gyropalm_control-1.1.0.dist-info/top_level.txt
gyropalm_control-1.1.0.dist-info/RECORD
