Metadata-Version: 2.1
Name: gyropalm-control
Version: 1.1.0
Summary: GyroPalm Python SDK for Robotic Control using Gestures
Project-URL: Source, https://github.com/GyroPalm/GyroPalm-Python-SDK
License-File: LICENSE
Requires-Dist: websockets >=7.0
